interpretercommand/__init__.py
interpretercommand/dispatcher.py
interpretercommand/exceptions.py
interpretercommand/interpreter.py
interpretercommand/parsers.py
interpretercommand/conditions/__init__.py
interpretercommand/conditions/boolean.py
interpretercommand/conditions/numeric.py
interpretercommand/conditions/relative.py
interpretercommand/conditions/string.py
interpretercommand/conditions/time.py
interpreter_command-2024.1.1.dist-info/LICENSE
interpreter_command-2024.1.1.dist-info/METADATA
interpreter_command-2024.1.1.dist-info/WHEEL
interpreter_command-2024.1.1.dist-info/top_level.txt
interpreter_command-2024.1.1.dist-info/RECORD
