Metadata-Version: 2.1
Name: interpreter-command
Version: 2024.1.1
Summary: A command interpreter engine for use with the RobotPy command-based library
Author-email: Kellen Watt <kellen@wattsoft.dev>
Classifier: Programming Language :: Python :: 3
Classifier: License :: OSI Approved :: MIT License
Classifier: Operating System :: OS Independent
Classifier: Framework :: Robot Framework :: Library
Requires-Python: >=3.10
License-File: LICENSE
Requires-Dist: robotpy
Requires-Dist: robotpy-commands-v2
